cli/__init__.py
cli/__main__.py
cli/patches/__init__.py
cli/patches/example.py
cli/patches/react.patch
cli/templates/react/.gitignore
cli/templates/react/index.html
cli/templates/react/package.json
cli/templates/react/vite.config.js
cli/templates/react/public/vite.svg
cli/templates/react/src/App.css
cli/templates/react/src/App.jsx
cli/templates/react/src/index.css
cli/templates/react/src/main.jsx
cli/templates/react/src/assets/react.svg
paneer/__init__.py
paneer/base.py
paneer/comms.py
paneer/linux.py
paneer/paneer.js
paneer/proto.py
paneer/windows.py
paneer/libs/Microsoft.Web.WebView2.Core.dll
paneer/libs/Microsoft.Web.WebView2.WinForms.dll
paneer/libs/WebView2Loader.dll
paneer-0.1.2.dist-info/METADATA
paneer-0.1.2.dist-info/WHEEL
paneer-0.1.2.dist-info/entry_points.txt
paneer-0.1.2.dist-info/top_level.txt
paneer-0.1.2.dist-info/RECORD
