Metadata-Version: 2.4
Name: paneer
Version: 0.1.2
Summary: Python package for Paneer, a framework to create desktop apps with web technologies and python.
Author-email: Om Thorat <thoratom1104@gmail.com>
License-Expression: MIT
Requires-Python: >=3.9
Requires-Dist: PyGObject; sys_platform != "win32"
Requires-Dist: inquirer
Requires-Dist: PyInstaller
Requires-Dist: pythonnet; sys_platform == "win32"
